<?xml version="1.0" encoding="utf-8"?>
<!-- Copyright 2023 - TODAY, Matheus Marques <matheus.marques@escodoo.com.br>
     License AGPL-3.0 or later (https://www.gnu.org/licenses/agpl). -->

<odoo>
    <record id="view_task_form2_inherit" model="ir.ui.view">
        <field name="name">project.task.inherit.advancement</field>
        <field name="model">project.task</field>
        <field name="inherit_id" ref="project.view_task_form2" />
        <field name="arch" type="xml">

            <field name="partner_id" position="after">

                <field name="advancement_percentage" widget="percentage" />

            </field>
            <field name="progress" position="after">

                <field name="advancement_progress" widget="progressbar" />

            </field>
        </field>
    </record>
</odoo>